odoo10_addon_account_check_printing_report_sslm102-10.0.1.0.0.99.dev4-py3.8-nspkg.pth
odoo/addons/account_check_printing_report_sslm102/README.rst
odoo/addons/account_check_printing_report_sslm102/__init__.py
odoo/addons/account_check_printing_report_sslm102/__manifest__.py
odoo/addons/account_check_printing_report_sslm102/data/account_payment_check_report_data.xml
odoo/addons/account_check_printing_report_sslm102/data/report_paperformat.xml
odoo/addons/account_check_printing_report_sslm102/data/report_paperformat_parameter.xml
odoo/addons/account_check_printing_report_sslm102/i18n/account_check_printing_report_dlt103.pot
odoo/addons/account_check_printing_report_sslm102/i18n/account_check_printing_report_sslm102.pot
odoo/addons/account_check_printing_report_sslm102/readme/CONFIGURE.rst
odoo/addons/account_check_printing_report_sslm102/readme/CONTRIBUTORS.rst
odoo/addons/account_check_printing_report_sslm102/readme/DESCRIPTION.rst
odoo/addons/account_check_printing_report_sslm102/readme/INSTALL.rst
odoo/addons/account_check_printing_report_sslm102/readme/USAGE.rst
odoo/addons/account_check_printing_report_sslm102/report/__init__.py
odoo/addons/account_check_printing_report_sslm102/report/account_check_writing_report.xml
odoo/addons/account_check_printing_report_sslm102/report/check_print.py
odoo/addons/account_check_printing_report_sslm102/static/description/icon.png
odoo/addons/account_check_printing_report_sslm102/static/description/index.html
odoo/addons/account_check_printing_report_sslm102/views/report_check.xml
odoo10_addon_account_check_printing_report_sslm102-10.0.1.0.0.99.dev4.dist-info/METADATA
odoo10_addon_account_check_printing_report_sslm102-10.0.1.0.0.99.dev4.dist-info/WHEEL
odoo10_addon_account_check_printing_report_sslm102-10.0.1.0.0.99.dev4.dist-info/namespace_packages.txt
odoo10_addon_account_check_printing_report_sslm102-10.0.1.0.0.99.dev4.dist-info/top_level.txt
odoo10_addon_account_check_printing_report_sslm102-10.0.1.0.0.99.dev4.dist-info/RECORD
